va_client/__init__.py
va_client/__main__.py
va_client/va_api.py
va_client/va_client.py
va_client/va_client_utils.py
vapps-1.1.9.dist-info/DESCRIPTION.rst
vapps-1.1.9.dist-info/METADATA
vapps-1.1.9.dist-info/RECORD
vapps-1.1.9.dist-info/WHEEL
vapps-1.1.9.dist-info/entry_points.txt
vapps-1.1.9.dist-info/metadata.json
vapps-1.1.9.dist-info/top_level.txt
