Metadata-Version: 2.0
Name: vapps
Version: 1.1.9
Summary: A command line client for executing va_master api commands. 
Home-page: https://github.com/pypa/sampleproject
Author: Nikola Dokoski
Author-email: nikola.dokoski@vapour-apps.com
License: MIT
Keywords: VapourApps
Platform: UNKNOWN
Classifier: Development Status :: 4 - Beta
Classifier: License :: OSI Approved :: MIT License
Classifier: Programming Language :: Python :: 2
Classifier: Programming Language :: Python :: 2.7
Requires-Dist: requests
